obt/__init__.py
obt/cli/__init__.py
obt/cli/main.py
obt/core/__init__.py
obt/core/settings.py
obt/core/tools.py
odoo_backup_tool-0.1.1.dist-info/METADATA
odoo_backup_tool-0.1.1.dist-info/WHEEL
odoo_backup_tool-0.1.1.dist-info/entry_points.txt
odoo_backup_tool-0.1.1.dist-info/top_level.txt
odoo_backup_tool-0.1.1.dist-info/RECORD
