Metadata-Version: 2.1
Name: odoo-backup-tool
Version: 0.1.1
Summary: Odoo Backup Tool
Home-page: https://github.com/royaurelien/odoo-backup-tool
Author: Aurelien ROY
Author-email: roy.aurelien@gmail.com
License: BSD 2-clause
Classifier: Development Status :: 4 - Beta
Classifier: Intended Audience :: Developers
Classifier: Topic :: Software Development :: Build Tools
Classifier: License :: OSI Approved :: BSD License
Classifier: Programming Language :: Python :: 3
Classifier: Programming Language :: Python :: 3.8
Classifier: Programming Language :: Python :: 3.9
Classifier: Programming Language :: Python :: 3.10
Classifier: Programming Language :: Python :: 3.11
Requires-Python: >=3.8
Requires-Dist: click
Requires-Dist: click-odoo-contrib
Requires-Dist: google
Requires-Dist: google-cloud-storage
Requires-Dist: pydantic
Requires-Dist: pydantic-settings
